unegui_property_models/__init__.py
unegui_property_models/db_settings.py
unegui_property_models/models.py
unegui_property_models-0.1.0.dist-info/METADATA
unegui_property_models-0.1.0.dist-info/WHEEL
unegui_property_models-0.1.0.dist-info/top_level.txt
unegui_property_models-0.1.0.dist-info/RECORD
