Metadata-Version: 2.1
Name: unegui-property-models
Version: 0.1.0
Summary: A library for shared SQLAlchemy models
Requires-Python: >=3.6
Requires-Dist: sqlalchemy
Requires-Dist: python-dotenv
Requires-Dist: psycopg2
